zoo/__init__.py
zoo/eval_benchmark.py
zoo/minigrid/__init__.py
zoo/minigrid/config/minigrid_muzero_rnd_config.py
zoo/minigrid/config/__init__.py
zoo/minigrid/config/minigrid_efficientzero_config.py
zoo/minigrid/config/minigrd_sampled_efficientzero_config.py
zoo/minigrid/config/minigrid_muzero_config.py
zoo/minigrid/entry/minigrid_eval.py
zoo/minigrid/entry/__init__.py
zoo/memory/__init__.py
zoo/memory/config/memory_sampled_efficientzero_config.py
zoo/memory/config/memory_efficientzero_config.py
zoo/memory/config/memory_muzero_config.py
zoo/memory/config/memory_muzero_rnd_config.py
zoo/memory/config/__init__.py
zoo/memory/config/memory_unizero_config.py
zoo/memory/entry/memory_eval.py
zoo/memory/entry/__init__.py
zoo/memory/envs/memory_lightzero_env.py
zoo/memory/envs/__init__.py
zoo/memory/envs/test_render.py
zoo/memory/envs/test_memory_lightzero_env.py
zoo/memory/envs/pycolab_tvt/game.py
zoo/memory/envs/pycolab_tvt/__init__.py
zoo/memory/envs/pycolab_tvt/key_to_door.py
zoo/memory/envs/pycolab_tvt/visual_match.py
zoo/memory/envs/pycolab_tvt/common.py
zoo/memory/envs/pycolab_tvt/human_player.py
zoo/memory/envs/pycolab_tvt/objects.py
zoo/dmc2gym/__init__.py
zoo/dmc2gym/envs/dmc2gym_lightzero_env.py
zoo/dmc2gym/envs/__init__.py
zoo/dmc2gym/envs/test_dmc2gym_env.py
zoo/jericho/__init__.py
zoo/jericho/envs/__init__.py
zoo/jericho/envs/test_jericho_env.py
zoo/jericho/envs/jericho_env.py
zoo/atari/read_atari_results_from_txt.py
zoo/atari/__init__.py
zoo/atari/compute_normalized_mean_and_median_atari100k.py
zoo/atari/config/atari_efficientzero_config.py
zoo/atari/config/atari_unizero_config.py
zoo/atari/config/atari_env_action_space_map.py
zoo/atari/config/atari_muzero_rnn_fullobs_config.py
zoo/atari/config/atari_muzero_context_config.py
zoo/atari/config/atari_efficientzero_ddp_config.py
zoo/atari/config/atari_unizero_stack4_config.py
zoo/atari/config/atari_unizero_segment_config.py
lightzero-0.2.0.dist-info/RECORD
lightzero-0.2.0.dist-info/WHEEL
lightzero-0.2.0.dist-info/top_level.txt
lightzero-0.2.0.dist-info/METADATA
lightzero-0.2.0.dist-info/licenses/LICENSE
